custjson/__init__.py
custjson/main.py
custjson-0.1.1.dist-info/METADATA
custjson-0.1.1.dist-info/WHEEL
custjson-0.1.1.dist-info/top_level.txt
custjson-0.1.1.dist-info/RECORD
