Metadata-Version: 2.1
Name: custjson
Version: 0.1.1
Summary: A package that manages JN formatted files (CustJSON specific JSON varient)
Author-email: FrienchBullPackages <frienchbulldoggo@gmail.com>
Project-URL: Homepage, https://github.com/frienchbulldog/custjson
Project-URL: Issues, https://github.com/frienchbulldog/custjson/issues
Classifier: Programming Language :: Python :: 3
Classifier: License :: OSI Approved :: MIT License
Classifier: Operating System :: OS Independent
Requires-Python: >=3.9
